lnl_computer/__init__.py
lnl_computer/_version.py
lnl_computer/likelihood.py
lnl_computer/logger.py
lnl_computer/mock_data.py
lnl_computer/cli/__init__.py
lnl_computer/cli/cli.py
lnl_computer/cli/main.py
lnl_computer/cosmic_integration/__init__.py
lnl_computer/cosmic_integration/mcz_grid.py
lnl_computer/cosmic_integration/star_formation_paramters.py
lnl_computer/observation/__init__.py
lnl_computer/observation/lvk_observation.py
lnl_computer/observation/mock_observation.py
lnl_computer/observation/observation.py
compas_surrogate.lnl_computer-0.2.0.dist-info/METADATA
compas_surrogate.lnl_computer-0.2.0.dist-info/WHEEL
compas_surrogate.lnl_computer-0.2.0.dist-info/entry_points.txt
compas_surrogate.lnl_computer-0.2.0.dist-info/top_level.txt
compas_surrogate.lnl_computer-0.2.0.dist-info/RECORD
