Metadata-Version: 2.1
Name: compas_surrogate.lnl_computer
Version: 0.2.0
Summary: COMPAS detection Likelihood computer
Author-email: Avi Vajpeyi <avi.vajpeyi@gmail.com>
Project-URL: Homepage, https://github.com/COMPAS-Surrogate/lnl_computer
Project-URL: Bug Reports, https://github.com/COMPAS-Surrogate/lnl_computer/issues
Project-URL: Source, https://github.com/COMPAS-Surrogate/lnl_computer/
Classifier: Development Status :: 3 - Alpha
Classifier: Intended Audience :: Science/Research
Classifier: License :: OSI Approved :: MIT License
Classifier: Operating System :: OS Independent
Classifier: Programming Language :: Python :: 3.9
Requires-Python: >=3.9
Requires-Dist: arviz
Requires-Dist: matplotlib
Requires-Dist: imageio
Requires-Dist: pygifsicle
Requires-Dist: bilby
Requires-Dist: loguru
Requires-Dist: colorlog
Requires-Dist: compas_surrogate.ogc4_interface
Requires-Dist: compas_python_utils
Provides-Extra: dev
Requires-Dist: pytest>=6.0; extra == "dev"
Requires-Dist: pytest-cov>=4.1.0; extra == "dev"
Requires-Dist: pre-commit; extra == "dev"
Requires-Dist: flake8>=5.0.4; extra == "dev"
Requires-Dist: black; extra == "dev"
Requires-Dist: jupyter-book; extra == "dev"
Requires-Dist: docformatter[tomli]; extra == "dev"
